axiprop/__init__.py
axiprop/backends.py
axiprop/common.py
axiprop/containers.py
axiprop/lib.py
axiprop/lib_compat.py
axiprop/steppers.py
axiprop/utils.py
axiprop/simulation/__init__.py
axiprop/simulation/diags.py
axiprop/simulation/ionization_inline.py
axiprop/simulation/lib.py
axiprop/simulation/plasma.py
axiprop/simulation/solvers.py
axiprop/simulation/steppers.py
axiprop-0.5.7.dist-info/LICENSE
axiprop-0.5.7.dist-info/METADATA
axiprop-0.5.7.dist-info/WHEEL
axiprop-0.5.7.dist-info/top_level.txt
axiprop-0.5.7.dist-info/RECORD
