Metadata-Version: 2.1
Name: axiprop
Version: 0.5.7
Summary: simple-to-use optical propagation tool
Home-page: https://github.com/hightower8083/axiprop
Author: Igor Andriyash
Maintainer: Igor Andriyash
Maintainer-email: igor.andriyash@gmail.com
License: BSD-3-Clause
Platform: any
Classifier: Programming Language :: Python
Classifier: Natural Language :: English
Classifier: Environment :: Console
Classifier: Intended Audience :: Science/Research
Classifier: Operating System :: OS Independent
Classifier: Topic :: Scientific/Engineering :: Physics
Classifier: Programming Language :: Python :: 3.6
Requires-Python: >=3.6
License-File: LICENSE
Requires-Dist: numpy
Requires-Dist: scipy
Requires-Dist: h5py
